[{"LastUpdateDateTime": "2015-05-18T15:39:25.26", "MatchResults": [{"ResultID": 54229, "PointsTeam2": 1, "ResultName": "Halbzeitergebnis", "PointsTeam1": 0, "ResultOrderID": 2, "ResultTypeID": 1, "ResultDescription": "Ergebnis nach Ende der ersten Halbzeit"}, {"ResultID": 54238, "PointsTeam2": 1, "ResultName": "Endergebnis", "PointsTeam1": 1, "ResultOrderID": 1, "ResultTypeID": 2, "ResultDescription": "Ergebnis nach Ende der offiziellen Spielzeit"}], "TimeZoneID": "W. Europe Standard Time", "Location": {"LocationID": 430, "LocationCity": "Hamburg", "LocationStadium": ""}, "Goals": [{"IsPenalty": false, "GoalGetterName": "Mehmedi", "GoalID": 38545, "ScoreTeam2": 1, "IsOwnGoal": false, "Comment": "", "ScoreTeam1": 0, "GoalGetterID": 11759, "MatchMinute": 25, "IsOvertime": false}, {"IsPenalty": false, "GoalGetterName": "Kacar", "GoalID": 38626, "ScoreTeam2": 1, "IsOwnGoal": false, "Comment": "", "ScoreTeam1": 1, "GoalGetterID": 107, "MatchMinute": 90, "IsOvertime": false}], "MatchIsFinished": true, "LeagueId": 720, "Team2": {"ShortName": "", "TeamId": 112, "TeamName": "SC Freiburg", "TeamIconUrl": "http://www.openligadb.de/images/teamicons/SC_Freiburg.gif"}, "Team1": {"ShortName": "HSV", "TeamId": 100, "TeamName": "Hamburger SV", "TeamIconUrl": "http://www.openligadb.de/images/teamicons/Hamburger_SV.gif"}, "Group": {"GroupID": 14594, "GroupName": "32. Spieltag", "GroupOrderID": 32}, "MatchID": 28279, "NumberOfViewers": null, "MatchDateTimeUTC": "2015-05-08T18:30:00Z", "MatchDateTime": "2015-05-08T20:30:00"}, {"LastUpdateDateTime": "2015-05-18T15:39:30.267", "MatchResults": [{"ResultID": 54251, "PointsTeam2": 0, "ResultName": "Endergebnis", "PointsTeam1": 2, "ResultOrderID": 1, "ResultTypeID": 2, "ResultDescription": "Ergebnis nach Ende der offiziellen Spielzeit"}, {"ResultID": 54252, "PointsTeam2": 0, "ResultName": "Halbzeitergebnis", "PointsTeam1": 1, "ResultOrderID": 2, "ResultTypeID": 1, "ResultDescription": "Ergebnis nach Ende der ersten Halbzeit"}], "TimeZoneID": "W. Europe Standard Time", "Location": {"LocationID": 744, "LocationCity": "Dortmund", "LocationStadium": ""}, "Goals": [{"IsPenalty": false, "GoalGetterName": "Subotic", "GoalID": 38570, "ScoreTeam2": 0, "IsOwnGoal": false, "Comment": "", "ScoreTeam1": 1, "GoalGetterID": 902, "MatchMinute": 9, "IsOvertime": false}, {"IsPenalty": false, "GoalGetterName": "Durm", "GoalID": 38585, "ScoreTeam2": 0, "IsOwnGoal": false, "Comment": "", "ScoreTeam1": 2, "GoalGetterID": 15040, "MatchMinute": 47, "IsOvertime": false}], "MatchIsFinished": true, "LeagueId": 720, "Team2": {"ShortName": "", "TeamId": 54, "TeamName": "Hertha BSC", "TeamIconUrl": "http://www.openligadb.de/images/teamicons/Hertha_BSC.gif"}, "Team1": {"ShortName": "BVB", "TeamId": 7, "TeamName": "Borussia Dortmund", "TeamIconUrl": "http://www.openligadb.de/images/teamicons/Borussia_Dortmund.gif"}, "Group": {"GroupID": 14594, "GroupName": "32. Spieltag", "GroupOrderID": 32}, "MatchID": 28264, "NumberOfViewers": null, "MatchDateTimeUTC": "2015-05-09T13:30:00Z", "MatchDateTime": "2015-05-09T15:30:00"}, {"LastUpdateDateTime": "2015-05-18T15:39:34.773", "MatchResults": [{"ResultID": 54253, "PointsTeam2": 1, "ResultName": "Endergebnis", "PointsTeam1": 0, "ResultOrderID": 1, "ResultTypeID": 2, "ResultDescription": "Ergebnis nach Ende der offiziellen Spielzeit"}, {"ResultID": 54254, "PointsTeam2": 0, "ResultName": "Halbzeitergebnis", "PointsTeam1": 0, "ResultOrderID": 2, "ResultTypeID": 1, "ResultDescription": "Ergebnis nach Ende der ersten Halbzeit"}], "TimeZoneID": "W. Europe Standard Time", "Location": {"LocationID": 573, "LocationCity": "M\u00fcnchen", "LocationStadium": ""}, "Goals": [{"IsPenalty": false, "GoalGetterName": "Bobadilla", "GoalID": 38592, "ScoreTeam2": 1, "IsOwnGoal": false, "Comment": "", "ScoreTeam1": 0, "GoalGetterID": 356, "MatchMinute": 71, "IsOvertime": false}], "MatchIsFinished": true, "LeagueId": 720, "Team2": {"ShortName": "", "TeamId": 95, "TeamName": "FC Augsburg", "TeamIconUrl": "http://www.openligadb.de/images/teamicons/FC_Augsburg.gif"}, "Team1": {"ShortName": "FC Bayern", "TeamId": 40, "TeamName": "Bayern M\u00fcnchen", "TeamIconUrl": "http://www.openligadb.de/images/teamicons/Bayern_Muenchen.gif"}, "Group": {"GroupID": 14594, "GroupName": "32. Spieltag", "GroupOrderID": 32}, "MatchID": 28274, "NumberOfViewers": null, "MatchDateTimeUTC": "2015-05-09T13:30:00Z", "MatchDateTime": "2015-05-09T15:30:00"}, {"LastUpdateDateTime": "2015-05-19T10:51:31.493", "MatchResults": [{"ResultID": 54255, "PointsTeam2": 0, "ResultName": "Endergebnis", "PointsTeam1": 3, "ResultOrderID": 1, "ResultTypeID": 2, "ResultDescription": "Ergebnis nach Ende der offiziellen Spielzeit"}, {"ResultID": 54256, "PointsTeam2": 0, "ResultName": "Halbzeitergebnis", "PointsTeam1": 0, "ResultOrderID": 2, "ResultTypeID": 1, "ResultDescription": "Ergebnis nach Ende der ersten Halbzeit"}], "TimeZoneID": "W. Europe Standard Time", "Location": {"LocationID": 844, "LocationCity": "Gladbach", "LocationStadium": ""}, "Goals": [{"IsPenalty": false, "GoalGetterName": "Kruse", "GoalID": 38588, "ScoreTeam2": 0, "IsOwnGoal": false, "Comment": "", "ScoreTeam1": 1, "GoalGetterID": 891, "MatchMinute": 50, "IsOvertime": false}, {"IsPenalty": false, "GoalGetterName": "Herrmann", "GoalID": 38596, "ScoreTeam2": 0, "IsOwnGoal": false, "Comment": "", "ScoreTeam1": 2, "GoalGetterID": 1439, "MatchMinute": 81, "IsOvertime": false}, {"IsPenalty": false, "GoalGetterName": "Traor\u00e9", "GoalID": 38598, "ScoreTeam2": 0, "IsOwnGoal": false, "Comment": "", "ScoreTeam1": 3, "GoalGetterID": 12028, "MatchMinute": 88, "IsOvertime": false}], "MatchIsFinished": true, "LeagueId": 720, "Team2": {"ShortName": "Leverkusen", "TeamId": 6, "TeamName": "Bayer 04 Leverkusen", "TeamIconUrl": "http://www.openligadb.de/images/teamicons/Bayer_Leverkusen.gif"}, "Team1": {"ShortName": "M\u00f6nchengladbach", "TeamId": 87, "TeamName": "Borussia M\u00f6nchengladbach", "TeamIconUrl": "http://www.openligadb.de/images/teamicons/Bor_Moenchengladbach.gif"}, "Group": {"GroupID": 14594, "GroupName": "32. Spieltag", "GroupOrderID": 32}, "MatchID": 28275, "NumberOfViewers": null, "MatchDateTimeUTC": "2015-05-09T13:30:00Z", "MatchDateTime": "2015-05-09T15:30:00"}, {"LastUpdateDateTime": "2015-05-18T15:39:46.613", "MatchResults": [{"ResultID": 54257, "PointsTeam2": 1, "ResultName": "Endergebnis", "PointsTeam1": 1, "ResultOrderID": 1, "ResultTypeID": 2, "ResultDescription": "Ergebnis nach Ende der offiziellen Spielzeit"}, {"ResultID": 54258, "PointsTeam2": 0, "ResultName": "Halbzeitergebnis", "PointsTeam1": 1, "ResultOrderID": 2, "ResultTypeID": 1, "ResultDescription": "Ergebnis nach Ende der ersten Halbzeit"}], "TimeZoneID": "W. Europe Standard Time", "Location": {"LocationID": 719, "LocationCity": "Hannover", "LocationStadium": ""}, "Goals": [{"IsPenalty": false, "GoalGetterName": "Stindl", "GoalID": 38574, "ScoreTeam2": 0, "IsOwnGoal": false, "Comment": "", "ScoreTeam1": 1, "GoalGetterID": 637, "MatchMinute": 21, "IsOvertime": false}, {"IsPenalty": false, "GoalGetterName": "Junuzovic", "GoalID": 38594, "ScoreTeam2": 1, "IsOwnGoal": false, "Comment": "", "ScoreTeam1": 1, "GoalGetterID": 2701, "MatchMinute": 78, "IsOvertime": false}], "MatchIsFinished": true, "LeagueId": 720, "Team2": {"ShortName": "", "TeamId": 134, "TeamName": "Werder Bremen", "TeamIconUrl": "http://www.openligadb.de/images/teamicons/werder_bremen.gif"}, "Team1": {"ShortName": "", "TeamId": 55, "TeamName": "Hannover 96", "TeamIconUrl": "http://www.openligadb.de/images/teamicons/Hannover_96.gif"}, "Group": {"GroupID": 14594, "GroupName": "32. Spieltag", "GroupOrderID": 32}, "MatchID": 28276, "NumberOfViewers": null, "MatchDateTimeUTC": "2015-05-09T13:30:00Z", "MatchDateTime": "2015-05-09T15:30:00"}, {"LastUpdateDateTime": "2015-05-18T15:39:52.747", "MatchResults": [{"ResultID": 54259, "PointsTeam2": 1, "ResultName": "Endergebnis", "PointsTeam1": 3, "ResultOrderID": 1, "ResultTypeID": 2, "ResultDescription": "Ergebnis nach Ende der offiziellen Spielzeit"}, {"ResultID": 54260, "PointsTeam2": 0, "ResultName": "Halbzeitergebnis", "PointsTeam1": 3, "ResultOrderID": 2, "ResultTypeID": 1, "ResultDescription": "Ergebnis nach Ende der ersten Halbzeit"}], "TimeZoneID": "W. Europe Standard Time", "Location": {"LocationID": 497, "LocationCity": "Frankfurt", "LocationStadium": ""}, "Goals": [{"IsPenalty": false, "GoalGetterName": "Oczipka", "GoalID": 38572, "ScoreTeam2": 0, "IsOwnGoal": false, "Comment": "", "ScoreTeam1": 1, "GoalGetterID": 15039, "MatchMinute": 18, "IsOvertime": false}, {"IsPenalty": false, "GoalGetterName": "Seferovic", "GoalID": 38576, "ScoreTeam2": 0, "IsOwnGoal": false, "Comment": "", "ScoreTeam1": 2, "GoalGetterID": 14260, "MatchMinute": 27, "IsOvertime": false}, {"IsPenalty": false, "GoalGetterName": "Chandler", "GoalID": 38578, "ScoreTeam2": 0, "IsOwnGoal": false, "Comment": "", "ScoreTeam1": 3, "GoalGetterID": 1813, "MatchMinute": 34, "IsOvertime": false}, {"IsPenalty": false, "GoalGetterName": "Volland", "GoalID": 38589, "ScoreTeam2": 1, "IsOwnGoal": false, "Comment": "", "ScoreTeam1": 3, "GoalGetterID": 1769, "MatchMinute": 51, "IsOvertime": false}], "MatchIsFinished": true, "LeagueId": 720, "Team2": {"ShortName": "", "TeamId": 123, "TeamName": "TSG 1899 Hoffenheim", "TeamIconUrl": "http://www.openligadb.de/images/teamicons/TSG_Hoffenheim.gif"}, "Team1": {"ShortName": "", "TeamId": 91, "TeamName": "Eintracht Frankfurt", "TeamIconUrl": "http://www.openligadb.de/images/teamicons/Eintracht_Frankfurt.gif"}, "Group": {"GroupID": 14594, "GroupName": "32. Spieltag", "GroupOrderID": 32}, "MatchID": 28277, "NumberOfViewers": null, "MatchDateTimeUTC": "2015-05-09T13:30:00Z", "MatchDateTime": "2015-05-09T15:30:00"}, {"LastUpdateDateTime": "2015-05-18T15:39:58.663", "MatchResults": [{"ResultID": 54275, "PointsTeam2": 0, "ResultName": "Endergebnis", "PointsTeam1": 2, "ResultOrderID": 1, "ResultTypeID": 2, "ResultDescription": "Ergebnis nach Ende der offiziellen Spielzeit"}, {"ResultID": 54276, "PointsTeam2": 0, "ResultName": "Halbzeitergebnis", "PointsTeam1": 0, "ResultOrderID": 2, "ResultTypeID": 1, "ResultDescription": "Ergebnis nach Ende der ersten Halbzeit"}], "TimeZoneID": "W. Europe Standard Time", "Location": {"LocationID": 613, "LocationCity": "Stuttgart", "LocationStadium": ""}, "Goals": [{"IsPenalty": false, "GoalGetterName": "Didavi", "GoalID": 38599, "ScoreTeam2": 0, "IsOwnGoal": false, "Comment": "", "ScoreTeam1": 1, "GoalGetterID": 32, "MatchMinute": 66, "IsOvertime": false}, {"IsPenalty": false, "GoalGetterName": "Kostic", "GoalID": 38616, "ScoreTeam2": 0, "IsOwnGoal": false, "Comment": "", "ScoreTeam1": 2, "GoalGetterID": 14821, "MatchMinute": 78, "IsOvertime": false}], "MatchIsFinished": true, "LeagueId": 720, "Team2": {"ShortName": "", "TeamId": 81, "TeamName": "1. FSV Mainz 05", "TeamIconUrl": "http://www.openligadb.de/images/teamicons/1_FSV_Mainz_05.gif"}, "Team1": {"ShortName": "", "TeamId": 16, "TeamName": "VfB Stuttgart", "TeamIconUrl": "http://www.openligadb.de/images/teamicons/VfB_Stuttgart.gif"}, "Group": {"GroupID": 14594, "GroupName": "32. Spieltag", "GroupOrderID": 32}, "MatchID": 28278, "NumberOfViewers": null, "MatchDateTimeUTC": "2015-05-09T16:30:00Z", "MatchDateTime": "2015-05-09T18:30:00"}, {"LastUpdateDateTime": "2015-05-18T15:40:03.58", "MatchResults": [{"ResultID": 54344, "PointsTeam2": 2, "ResultName": "Halbzeitergebnis", "PointsTeam1": 0, "ResultOrderID": 2, "ResultTypeID": 1, "ResultDescription": "Ergebnis nach Ende der ersten Halbzeit"}, {"ResultID": 54345, "PointsTeam2": 3, "ResultName": "Endergebnis", "PointsTeam1": 1, "ResultOrderID": 1, "ResultTypeID": 2, "ResultDescription": "Ergebnis nach Ende der offiziellen Spielzeit"}], "TimeZoneID": "W. Europe Standard Time", "Location": {"LocationID": 810, "LocationCity": "Paderborn", "LocationStadium": ""}, "Goals": [{"IsPenalty": false, "GoalGetterName": "Klose", "GoalID": 38675, "ScoreTeam2": 1, "IsOwnGoal": false, "Comment": "", "ScoreTeam1": 0, "GoalGetterID": 1046, "MatchMinute": 15, "IsOvertime": false}, {"IsPenalty": false, "GoalGetterName": "Dost", "GoalID": 38676, "ScoreTeam2": 2, "IsOwnGoal": false, "Comment": "", "ScoreTeam1": 0, "GoalGetterID": 6795, "MatchMinute": 25, "IsOvertime": false}, {"IsPenalty": false, "GoalGetterName": "Dost", "GoalID": 38691, "ScoreTeam2": 3, "IsOwnGoal": false, "Comment": "", "ScoreTeam1": 0, "GoalGetterID": 6795, "MatchMinute": 82, "IsOvertime": false}, {"IsPenalty": false, "GoalGetterName": "Rupp", "GoalID": 38692, "ScoreTeam2": 3, "IsOwnGoal": false, "Comment": "", "ScoreTeam1": 1, "GoalGetterID": 1626, "MatchMinute": 90, "IsOvertime": false}], "MatchIsFinished": true, "LeagueId": 720, "Team2": {"ShortName": "VfL Wolfsburg", "TeamId": 131, "TeamName": "VfL Wolfsburg", "TeamIconUrl": "http://www.openligadb.de/images/teamicons/VfL_Wolfsburg.gif"}, "Team1": {"ShortName": "", "TeamId": 31, "TeamName": "SC Paderborn 07", "TeamIconUrl": "http://www.openligadb.de/images/teamicons/SC_Paderborn_07.gif"}, "Group": {"GroupID": 14594, "GroupName": "32. Spieltag", "GroupOrderID": 32}, "MatchID": 28281, "NumberOfViewers": null, "MatchDateTimeUTC": "2015-05-10T13:30:00Z", "MatchDateTime": "2015-05-10T15:30:00"}, {"LastUpdateDateTime": "2015-05-18T15:40:08.723", "MatchResults": [{"ResultID": 54359, "PointsTeam2": 0, "ResultName": "Endergebnis", "PointsTeam1": 2, "ResultOrderID": 1, "ResultTypeID": 2, "ResultDescription": "Ergebnis nach Ende der offiziellen Spielzeit"}, {"ResultID": 54360, "PointsTeam2": 0, "ResultName": "Halbzeitergebnis", "PointsTeam1": 1, "ResultOrderID": 2, "ResultTypeID": 1, "ResultDescription": "Ergebnis nach Ende der ersten Halbzeit"}], "TimeZoneID": "W. Europe Standard Time", "Location": {"LocationID": 166, "LocationCity": "K\u00f6ln", "LocationStadium": ""}, "Goals": [{"IsPenalty": false, "GoalGetterName": "Risse", "GoalID": 38693, "ScoreTeam2": 0, "IsOwnGoal": false, "Comment": "", "ScoreTeam1": 1, "GoalGetterID": 1473, "MatchMinute": 34, "IsOvertime": false}, {"IsPenalty": false, "GoalGetterName": "Gerhardt", "GoalID": 38702, "ScoreTeam2": 0, "IsOwnGoal": false, "Comment": "", "ScoreTeam1": 2, "GoalGetterID": 11633, "MatchMinute": 89, "IsOvertime": false}], "MatchIsFinished": true, "LeagueId": 720, "Team2": {"ShortName": "Schalke", "TeamId": 9, "TeamName": "FC Schalke 04", "TeamIconUrl": "http://www.openligadb.de/images/teamicons/FC_Schalke_04.gif"}, "Team1": {"ShortName": "", "TeamId": 65, "TeamName": "1. FC K\u00f6ln", "TeamIconUrl": "http://www.openligadb.de/images/teamicons/1_FC_Koeln.gif"}, "Group": {"GroupID": 14594, "GroupName": "32. Spieltag", "GroupOrderID": 32}, "MatchID": 28280, "NumberOfViewers": null, "MatchDateTimeUTC": "2015-05-10T15:30:00Z", "MatchDateTime": "2015-05-10T17:30:00"}]