[{"LastUpdateDateTime": "2013-09-21T17:21:23.417", "MatchResults": [{"ResultID": 38252, "PointsTeam2": 0, "ResultName": "Halbzeit", "PointsTeam1": 2, "ResultOrderID": 2, "ResultTypeID": 1, "ResultDescription": "Ergebnis nach Ende der ersten Halbzeit"}, {"ResultID": 38274, "PointsTeam2": 1, "ResultName": "Endergebnis", "PointsTeam1": 4, "ResultOrderID": 1, "ResultTypeID": 2, "ResultDescription": "Ergebnis nach Ende der offiziellen Spielzeit"}], "TimeZoneID": "W. Europe Standard Time", "Location": {"LocationID": 445, "LocationCity": "M\u00f6nchengladbach", "LocationStadium": "Stadion im Borussia-Park"}, "Goals": [{"IsPenalty": false, "GoalGetterName": "Wendt ", "GoalID": 22090, "ScoreTeam2": 0, "IsOwnGoal": false, "Comment": null, "ScoreTeam1": 1, "GoalGetterID": 8310, "MatchMinute": 22, "IsOvertime": false}, {"IsPenalty": false, "GoalGetterName": "Raffael", "GoalID": 22091, "ScoreTeam2": 0, "IsOwnGoal": false, "Comment": null, "ScoreTeam1": 2, "GoalGetterID": 60, "MatchMinute": 31, "IsOvertime": false}, {"IsPenalty": false, "GoalGetterName": "Boland", "GoalID": 22092, "ScoreTeam2": 1, "IsOwnGoal": false, "Comment": null, "ScoreTeam1": 2, "GoalGetterID": 2511, "MatchMinute": 58, "IsOvertime": false}, {"IsPenalty": true, "GoalGetterName": "Kruse, Max", "GoalID": 22093, "ScoreTeam2": 1, "IsOwnGoal": false, "Comment": null, "ScoreTeam1": 3, "GoalGetterID": 11539, "MatchMinute": 72, "IsOvertime": false}, {"IsPenalty": false, "GoalGetterName": "Raffael", "GoalID": 22094, "ScoreTeam2": 1, "IsOwnGoal": false, "Comment": null, "ScoreTeam1": 4, "GoalGetterID": 60, "MatchMinute": 75, "IsOvertime": false}], "MatchIsFinished": true, "LeagueId": 623, "Team2": {"ShortName": "", "TeamId": 74, "TeamName": "Eintracht Braunschweig", "TeamIconUrl": "http://www.openligadb.de/images/teamicons/Eintracht_Braunschweig.gif"}, "Team1": {"ShortName": "M\u00f6nchengladbach", "TeamId": 87, "TeamName": "Borussia M\u00f6nchengladbach", "TeamIconUrl": "http://www.openligadb.de/images/teamicons/Bor_Moenchengladbach.gif"}, "Group": {"GroupID": 13613, "GroupName": "6. Spieltag", "GroupOrderID": 6}, "MatchID": 23825, "NumberOfViewers": 50064, "MatchDateTimeUTC": "2013-09-20T18:30:00Z", "MatchDateTime": "2013-09-20T20:30:00"}, {"LastUpdateDateTime": "2013-09-21T19:38:41.417", "MatchResults": [{"ResultID": 38270, "PointsTeam2": 4, "ResultName": "Endergebnis", "PointsTeam1": 1, "ResultOrderID": 1, "ResultTypeID": 2, "ResultDescription": "Ergebnis nach Ende der offiziellen Spielzeit"}, {"ResultID": 38271, "PointsTeam2": 3, "ResultName": "Halbzeit", "PointsTeam1": 0, "ResultOrderID": 2, "ResultTypeID": 1, "ResultDescription": "Ergebnis nach Ende der ersten Halbzeit"}], "TimeZoneID": "W. Europe Standard Time", "Location": {"LocationID": 465, "LocationCity": "Mainz", "LocationStadium": "Coface Arena"}, "Goals": [{"IsPenalty": false, "GoalGetterName": "Kruse", "GoalID": 22113, "ScoreTeam2": 1, "IsOwnGoal": false, "Comment": null, "ScoreTeam1": 0, "GoalGetterID": 891, "MatchMinute": 19, "IsOvertime": false}, {"IsPenalty": false, "GoalGetterName": "Bender", "GoalID": 22116, "ScoreTeam2": 2, "IsOwnGoal": false, "Comment": null, "ScoreTeam1": 0, "GoalGetterID": 935, "MatchMinute": 38, "IsOvertime": false}, {"IsPenalty": false, "GoalGetterName": "Kruse", "GoalID": 22118, "ScoreTeam2": 3, "IsOwnGoal": false, "Comment": null, "ScoreTeam1": 0, "GoalGetterID": 891, "MatchMinute": 45, "IsOvertime": false}, {"IsPenalty": false, "GoalGetterName": "Kie\u00dfling", "GoalID": 22123, "ScoreTeam2": 4, "IsOwnGoal": false, "Comment": null, "ScoreTeam1": 0, "GoalGetterID": 114, "MatchMinute": 59, "IsOvertime": false}, {"IsPenalty": false, "GoalGetterName": "Malli", "GoalID": 22124, "ScoreTeam2": 4, "IsOwnGoal": false, "Comment": null, "ScoreTeam1": 1, "GoalGetterID": 1521, "MatchMinute": 82, "IsOvertime": false}], "MatchIsFinished": true, "LeagueId": 623, "Team2": {"ShortName": "Leverkusen", "TeamId": 6, "TeamName": "Bayer 04 Leverkusen", "TeamIconUrl": "http://www.openligadb.de/images/teamicons/Bayer_Leverkusen.gif"}, "Team1": {"ShortName": "", "TeamId": 81, "TeamName": "1. FSV Mainz 05", "TeamIconUrl": "http://www.openligadb.de/images/teamicons/1_FSV_Mainz_05.gif"}, "Group": {"GroupID": 13613, "GroupName": "6. Spieltag", "GroupOrderID": 6}, "MatchID": 23831, "NumberOfViewers": 28617, "MatchDateTimeUTC": "2013-09-21T13:30:00Z", "MatchDateTime": "2013-09-21T15:30:00"}, {"LastUpdateDateTime": "2013-09-21T19:41:14.617", "MatchResults": [{"ResultID": 38268, "PointsTeam2": 2, "ResultName": "Endergebnis", "PointsTeam1": 0, "ResultOrderID": 1, "ResultTypeID": 2, "ResultDescription": "Ergebnis nach Ende der offiziellen Spielzeit"}, {"ResultID": 38269, "PointsTeam2": 1, "ResultName": "Halbzeit", "PointsTeam1": 0, "ResultOrderID": 2, "ResultTypeID": 1, "ResultDescription": "Ergebnis nach Ende der ersten Halbzeit"}], "TimeZoneID": "W. Europe Standard Time", "Location": {"LocationID": 404, "LocationCity": "Hamburg ", "LocationStadium": "Imtech Arena"}, "Goals": [{"IsPenalty": false, "GoalGetterName": "Petersen", "GoalID": 22114, "ScoreTeam2": 1, "IsOwnGoal": false, "Comment": null, "ScoreTeam1": 0, "GoalGetterID": 1395, "MatchMinute": 32, "IsOvertime": false}, {"IsPenalty": false, "GoalGetterName": "Petersen", "GoalID": 22128, "ScoreTeam2": 2, "IsOwnGoal": false, "Comment": null, "ScoreTeam1": 0, "GoalGetterID": 1395, "MatchMinute": 94, "IsOvertime": false}], "MatchIsFinished": true, "LeagueId": 623, "Team2": {"ShortName": "", "TeamId": 134, "TeamName": "Werder Bremen", "TeamIconUrl": "http://www.openligadb.de/images/teamicons/werder_bremen.gif"}, "Team1": {"ShortName": "HSV", "TeamId": 100, "TeamName": "Hamburger SV", "TeamIconUrl": "http://www.openligadb.de/images/teamicons/Hamburger_SV.gif"}, "Group": {"GroupID": 13613, "GroupName": "6. Spieltag", "GroupOrderID": 6}, "MatchID": 23833, "NumberOfViewers": 53290, "MatchDateTimeUTC": "2013-09-21T13:30:00Z", "MatchDateTime": "2013-09-21T15:30:00"}, {"LastUpdateDateTime": "2013-09-22T21:59:43.12", "MatchResults": [{"ResultID": 38272, "PointsTeam2": 1, "ResultName": "Endergebnis", "PointsTeam1": 2, "ResultOrderID": 1, "ResultTypeID": 2, "ResultDescription": "Ergebnis nach Ende der offiziellen Spielzeit"}, {"ResultID": 38273, "PointsTeam2": 0, "ResultName": "Halbzeit", "PointsTeam1": 0, "ResultOrderID": 2, "ResultTypeID": 1, "ResultDescription": "Ergebnis nach Ende der ersten Halbzeit"}], "TimeZoneID": "W. Europe Standard Time", "Location": {"LocationID": 845, "LocationCity": "Hannover", "LocationStadium": "HDI Arena"}, "Goals": [{"IsPenalty": true, "GoalGetterName": "Verhaegh", "GoalID": 22121, "ScoreTeam2": 1, "IsOwnGoal": false, "Comment": null, "ScoreTeam1": 0, "GoalGetterID": 1925, "MatchMinute": 50, "IsOvertime": false}, {"IsPenalty": false, "GoalGetterName": "sobiech", "GoalID": 22122, "ScoreTeam2": 1, "IsOwnGoal": false, "Comment": null, "ScoreTeam1": 1, "GoalGetterID": 4304, "MatchMinute": 60, "IsOvertime": false}, {"IsPenalty": true, "GoalGetterName": "Huszti", "GoalID": 22125, "ScoreTeam2": 1, "IsOwnGoal": false, "Comment": null, "ScoreTeam1": 2, "GoalGetterID": 7272, "MatchMinute": 89, "IsOvertime": false}], "MatchIsFinished": true, "LeagueId": 623, "Team2": {"ShortName": "", "TeamId": 95, "TeamName": "FC Augsburg", "TeamIconUrl": "http://www.openligadb.de/images/teamicons/FC_Augsburg.gif"}, "Team1": {"ShortName": "", "TeamId": 55, "TeamName": "Hannover 96", "TeamIconUrl": "http://www.openligadb.de/images/teamicons/Hannover_96.gif"}, "Group": {"GroupID": 13613, "GroupName": "6. Spieltag", "GroupOrderID": 6}, "MatchID": 23827, "NumberOfViewers": 39200, "MatchDateTimeUTC": "2013-09-21T13:30:00Z", "MatchDateTime": "2013-09-21T15:30:00"}, {"LastUpdateDateTime": "2013-09-21T19:36:48.307", "MatchResults": [{"ResultID": 38266, "PointsTeam2": 1, "ResultName": "Endergebnis", "PointsTeam1": 2, "ResultOrderID": 1, "ResultTypeID": 2, "ResultDescription": "Ergebnis nach Ende der offiziellen Spielzeit"}, {"ResultID": 38267, "PointsTeam2": 1, "ResultName": "Halbzeit", "PointsTeam1": 1, "ResultOrderID": 2, "ResultTypeID": 1, "ResultDescription": "Ergebnis nach Ende der ersten Halbzeit"}], "TimeZoneID": "W. Europe Standard Time", "Location": {"LocationID": 20, "LocationCity": "Wolfsburg", "LocationStadium": "Volkswagen Arena "}, "Goals": [{"IsPenalty": false, "GoalGetterName": "Modeste", "GoalID": 22112, "ScoreTeam2": 1, "IsOwnGoal": false, "Comment": null, "ScoreTeam1": 0, "GoalGetterID": 11344, "MatchMinute": 15, "IsOvertime": false}, {"IsPenalty": false, "GoalGetterName": "Olic", "GoalID": 22117, "ScoreTeam2": 1, "IsOwnGoal": false, "Comment": null, "ScoreTeam1": 1, "GoalGetterID": 116, "MatchMinute": 44, "IsOvertime": false}, {"IsPenalty": false, "GoalGetterName": "Olic", "GoalID": 22119, "ScoreTeam2": 1, "IsOwnGoal": false, "Comment": null, "ScoreTeam1": 2, "GoalGetterID": 116, "MatchMinute": 48, "IsOvertime": false}], "MatchIsFinished": true, "LeagueId": 623, "Team2": {"ShortName": "", "TeamId": 123, "TeamName": "TSG 1899 Hoffenheim", "TeamIconUrl": "http://www.openligadb.de/images/teamicons/TSG_Hoffenheim.gif"}, "Team1": {"ShortName": "VfL Wolfsburg", "TeamId": 131, "TeamName": "VfL Wolfsburg", "TeamIconUrl": "http://www.openligadb.de/images/teamicons/VfL_Wolfsburg.gif"}, "Group": {"GroupID": 13613, "GroupName": "6. Spieltag", "GroupOrderID": 6}, "MatchID": 23828, "NumberOfViewers": 29837, "MatchDateTimeUTC": "2013-09-21T13:30:00Z", "MatchDateTime": "2013-09-21T15:30:00"}, {"LastUpdateDateTime": "2013-11-01T22:26:07.85", "MatchResults": [{"ResultID": 38264, "PointsTeam2": 1, "ResultName": "Endergebnis", "PointsTeam1": 1, "ResultOrderID": 1, "ResultTypeID": 2, "ResultDescription": "Ergebnis nach Ende der offiziellen Spielzeit"}, {"ResultID": 38265, "PointsTeam2": 1, "ResultName": "Halbzeit", "PointsTeam1": 0, "ResultOrderID": 2, "ResultTypeID": 1, "ResultDescription": "Ergebnis nach Ende der ersten Halbzeit"}], "TimeZoneID": "W. Europe Standard Time", "Location": {"LocationID": 800, "LocationCity": "N\u00fcrnberg", "LocationStadium": "Grundig Stadion"}, "Goals": [{"IsPenalty": false, "GoalGetterName": "Schmelzer", "GoalID": 22115, "ScoreTeam2": 1, "IsOwnGoal": false, "Comment": null, "ScoreTeam1": 0, "GoalGetterID": 1441, "MatchMinute": 37, "IsOvertime": false}, {"IsPenalty": false, "GoalGetterName": "Nilsson", "GoalID": 22120, "ScoreTeam2": 1, "IsOwnGoal": false, "Comment": null, "ScoreTeam1": 1, "GoalGetterID": 760, "MatchMinute": 51, "IsOvertime": false}], "MatchIsFinished": true, "LeagueId": 623, "Team2": {"ShortName": "BVB", "TeamId": 7, "TeamName": "Borussia Dortmund", "TeamIconUrl": "http://www.openligadb.de/images/teamicons/Borussia_Dortmund.gif"}, "Team1": {"ShortName": "", "TeamId": 79, "TeamName": "1. FC N\u00fcrnberg", "TeamIconUrl": "http://www.openligadb.de/images/teamicons/1_FC_Nuernberg.gif"}, "Group": {"GroupID": 13613, "GroupName": "6. Spieltag", "GroupOrderID": 6}, "MatchID": 23829, "NumberOfViewers": 50000, "MatchDateTimeUTC": "2013-09-21T13:30:00Z", "MatchDateTime": "2013-09-21T15:30:00"}, {"LastUpdateDateTime": "2013-09-21T20:16:41.617", "MatchResults": [{"ResultID": 38290, "PointsTeam2": 2, "ResultName": "Halbzeit", "PointsTeam1": 0, "ResultOrderID": 2, "ResultTypeID": 1, "ResultDescription": "Ergebnis nach Ende der ersten Halbzeit"}, {"ResultID": 38291, "PointsTeam2": 4, "ResultName": "Endergebnis", "PointsTeam1": 0, "ResultOrderID": 1, "ResultTypeID": 2, "ResultDescription": "Ergebnis nach Ende der offiziellen Spielzeit"}], "TimeZoneID": "W. Europe Standard Time", "Location": {"LocationID": 403, "LocationCity": "Gelsenkirchen", "LocationStadium": "Veltins-Arena"}, "Goals": [{"IsPenalty": false, "GoalGetterName": "Schweinsteiger", "GoalID": 22138, "ScoreTeam2": 1, "IsOwnGoal": false, "Comment": null, "ScoreTeam1": 0, "GoalGetterID": 7, "MatchMinute": 21, "IsOvertime": false}, {"IsPenalty": false, "GoalGetterName": "Mandzukic, Mario", "GoalID": 22139, "ScoreTeam2": 2, "IsOwnGoal": false, "Comment": null, "ScoreTeam1": 0, "GoalGetterID": 11532, "MatchMinute": 22, "IsOvertime": false}, {"IsPenalty": false, "GoalGetterName": "Rib\u00e9ry, Frank", "GoalID": 22140, "ScoreTeam2": 3, "IsOwnGoal": false, "Comment": null, "ScoreTeam1": 0, "GoalGetterID": 11848, "MatchMinute": 74, "IsOvertime": false}, {"IsPenalty": false, "GoalGetterName": "Pizarro", "GoalID": 22141, "ScoreTeam2": 4, "IsOwnGoal": false, "Comment": null, "ScoreTeam1": 0, "GoalGetterID": 309, "MatchMinute": 84, "IsOvertime": false}], "MatchIsFinished": true, "LeagueId": 623, "Team2": {"ShortName": "FC Bayern", "TeamId": 40, "TeamName": "Bayern M\u00fcnchen", "TeamIconUrl": "http://www.openligadb.de/images/teamicons/Bayern_Muenchen.gif"}, "Team1": {"ShortName": "Schalke", "TeamId": 9, "TeamName": "FC Schalke 04", "TeamIconUrl": "http://www.openligadb.de/images/teamicons/FC_Schalke_04.gif"}, "Group": {"GroupID": 13613, "GroupName": "6. Spieltag", "GroupOrderID": 6}, "MatchID": 23824, "NumberOfViewers": 61973, "MatchDateTimeUTC": "2013-09-21T16:30:00Z", "MatchDateTime": "2013-09-21T18:30:00"}, {"LastUpdateDateTime": "2013-09-22T22:01:42.83", "MatchResults": [{"ResultID": 38292, "PointsTeam2": 1, "ResultName": "Endergebnis", "PointsTeam1": 1, "ResultOrderID": 1, "ResultTypeID": 2, "ResultDescription": "Ergebnis nach Ende der offiziellen Spielzeit"}, {"ResultID": 38293, "PointsTeam2": 1, "ResultName": "Halbzeit", "PointsTeam1": 1, "ResultOrderID": 2, "ResultTypeID": 1, "ResultDescription": "Ergebnis nach Ende der ersten Halbzeit"}], "TimeZoneID": "W. Europe Standard Time", "Location": {"LocationID": 516, "LocationCity": "Freiburg", "LocationStadium": "MAGE SOLAR Stadion"}, "Goals": [{"IsPenalty": false, "GoalGetterName": "Mehmedi", "GoalID": 22142, "ScoreTeam2": 0, "IsOwnGoal": false, "Comment": null, "ScoreTeam1": 1, "GoalGetterID": 11759, "MatchMinute": 6, "IsOvertime": false}, {"IsPenalty": false, "GoalGetterName": "Skjelbred", "GoalID": 22143, "ScoreTeam2": 1, "IsOwnGoal": false, "Comment": null, "ScoreTeam1": 1, "GoalGetterID": 11849, "MatchMinute": 38, "IsOvertime": false}], "MatchIsFinished": true, "LeagueId": 623, "Team2": {"ShortName": "", "TeamId": 54, "TeamName": "Hertha BSC", "TeamIconUrl": "http://www.openligadb.de/images/teamicons/Hertha_BSC.gif"}, "Team1": {"ShortName": "", "TeamId": 112, "TeamName": "SC Freiburg", "TeamIconUrl": "http://www.openligadb.de/images/teamicons/SC_Freiburg.gif"}, "Group": {"GroupID": 13613, "GroupName": "6. Spieltag", "GroupOrderID": 6}, "MatchID": 23830, "NumberOfViewers": 23200, "MatchDateTimeUTC": "2013-09-22T13:30:00Z", "MatchDateTime": "2013-09-22T15:30:00"}, {"LastUpdateDateTime": "2013-09-22T22:02:40.217", "MatchResults": [{"ResultID": 38318, "PointsTeam2": 1, "ResultName": "Endergebnis", "PointsTeam1": 1, "ResultOrderID": 1, "ResultTypeID": 2, "ResultDescription": "Ergebnis nach Ende der offiziellen Spielzeit"}, {"ResultID": 38319, "PointsTeam2": 1, "ResultName": "Halbzeit", "PointsTeam1": 1, "ResultOrderID": 2, "ResultTypeID": 1, "ResultDescription": "Ergebnis nach Ende der ersten Halbzeit"}], "TimeZoneID": "W. Europe Standard Time", "Location": {"LocationID": 493, "LocationCity": "Stuttgart", "LocationStadium": "Mercedes-Benz Arena"}, "Goals": [{"IsPenalty": false, "GoalGetterName": "Russ", "GoalID": 22169, "ScoreTeam2": 1, "IsOwnGoal": false, "Comment": null, "ScoreTeam1": 0, "GoalGetterID": 721, "MatchMinute": 14, "IsOvertime": false}, {"IsPenalty": false, "GoalGetterName": "Werner", "GoalID": 22170, "ScoreTeam2": 1, "IsOwnGoal": false, "Comment": null, "ScoreTeam1": 1, "GoalGetterID": 185, "MatchMinute": 16, "IsOvertime": false}], "MatchIsFinished": true, "LeagueId": 623, "Team2": {"ShortName": "", "TeamId": 91, "TeamName": "Eintracht Frankfurt", "TeamIconUrl": "http://www.openligadb.de/images/teamicons/Eintracht_Frankfurt.gif"}, "Team1": {"ShortName": "", "TeamId": 16, "TeamName": "VfB Stuttgart", "TeamIconUrl": "http://www.openligadb.de/images/teamicons/VfB_Stuttgart.gif"}, "Group": {"GroupID": 13613, "GroupName": "6. Spieltag", "GroupOrderID": 6}, "MatchID": 23826, "NumberOfViewers": 44810, "MatchDateTimeUTC": "2013-09-22T15:30:00Z", "MatchDateTime": "2013-09-22T17:30:00"}]